ptmethods/__init__.py
ptmethods/_version.py
ptmethods/ptmethods.py
ptmethods/modules/__init__.py
ptmethods/modules/helpers.py
ptmethods-1.0.7.dist-info/licenses/LICENSE
ptmethods-1.0.7.dist-info/METADATA
ptmethods-1.0.7.dist-info/WHEEL
ptmethods-1.0.7.dist-info/entry_points.txt
ptmethods-1.0.7.dist-info/top_level.txt
ptmethods-1.0.7.dist-info/RECORD
